{
  "schemaVersion": "praxis.codeFactGraph.v1",
  "root": "/repo",
  "generatedAt": "2026-05-25T00:00:00.000Z",
  "provider": {
    "name": "native-heuristic",
    "source": "native",
    "version": "0.1.0-alpha.0",
    "runId": "code-facts:native:fixture",
    "capabilities": ["file_structure", "imports_exports"]
  },
  "files": [
    {
      "id": "code:file:packages-core-src-index-ts",
      "path": "packages/core/src/index.ts",
      "language": "TypeScript",
      "extension": ".ts",
      "sizeBytes": 28,
      "lineCount": 1,
      "roleHint": "domain",
      "nodeIds": ["code:file:packages-core-src-index-ts"],
      "evidence": [
        {
          "source": "repository_scan",
          "filePath": "packages/core/src/index.ts"
        }
      ]
    }
  ],
  "nodes": [
    {
      "id": "code:project-root",
      "kind": "project",
      "name": "repo",
      "qualifiedName": "repo",
      "filePath": ".",
      "language": "Repository",
      "evidence": [
        {
          "source": "repository_scan",
          "filePath": "."
        }
      ]
    },
    {
      "id": "code:file:packages-core-src-index-ts",
      "kind": "file",
      "name": "index.ts",
      "qualifiedName": "packages/core/src/index.ts",
      "filePath": "packages/core/src/index.ts",
      "language": "TypeScript",
      "range": {
        "startLine": 1,
        "endLine": 1
      },
      "evidence": [
        {
          "source": "repository_scan",
          "filePath": "packages/core/src/index.ts"
        }
      ]
    }
  ],
  "edges": [
    {
      "id": "code-edge:project-contains-core-index",
      "kind": "contains",
      "sourceId": "code:project-root",
      "targetId": "code:file:packages-core-src-index-ts",
      "filePath": "packages/core/src/index.ts",
      "confidence": 1,
      "evidence": [
        {
          "source": "repository_scan",
          "filePath": "packages/core/src/index.ts"
        }
      ]
    }
  ],
  "statistics": {
    "fileCount": 1,
    "nodeCount": 2,
    "edgeCount": 1,
    "filesByLanguage": {
      "TypeScript": 1
    },
    "nodesByKind": {
      "project": 1,
      "file": 1
    },
    "edgesByKind": {
      "contains": 1
    }
  },
  "warnings": []
}
